README.rst
setup.cfg
setup.py
github_compose/__init__.py
github_compose/cli.py
github_compose.egg-info/PKG-INFO
github_compose.egg-info/SOURCES.txt
github_compose.egg-info/dependency_links.txt
github_compose.egg-info/entry_points.txt
github_compose.egg-info/not-zip-safe
github_compose.egg-info/requires.txt
github_compose.egg-info/top_level.txt