Metadata-Version: 2.1
Name: github-compose
Version: 0.2.3
Summary: Orchestrate your GitHub repositories like ``docker-compose`` orchestrates your Docker containers.
Home-page: https://github.com/jacquerie/github-compose
Author: Jacopo Notarstefano
Author-email: jacopo.notarstefano@gmail.com
License: MIT
Platform: any
Classifier: Development Status :: 1 - Planning
Classifier: Environment :: Console
Classifier: Intended Audience :: Developers
Classifier: License :: OSI Approved :: MIT License
Classifier: Operating System :: OS Independent
Classifier: Programming Language :: Python
Classifier: Programming Language :: Python :: 2
Classifier: Programming Language :: Python :: 2.7
Classifier: Programming Language :: Python :: 3
Classifier: Programming Language :: Python :: 3.4
Classifier: Programming Language :: Python :: 3.5
Classifier: Programming Language :: Python :: 3.6
Classifier: Topic :: Software Development :: Libraries :: Python Modules
Classifier: Topic :: Software Development :: Libraries
Classifier: Topic :: Utilities
Provides-Extra: docs
Provides-Extra: tests
Provides-Extra: all
